bizstats_stripe_billing/__init__.py
bizstats_stripe_billing/billing.py
bizstats_stripe_billing/client.py
bizstats_stripe_billing/config.py
bizstats_stripe_billing/exceptions.py
bizstats_stripe_billing/models/__init__.py
bizstats_stripe_billing/models/enums.py
bizstats_stripe_billing/models/results.py
bizstats_stripe_billing/models/schemas.py
bizstats_stripe_billing/webhooks/__init__.py
bizstats_stripe_billing/webhooks/events.py
bizstats_stripe_billing/webhooks/handler.py
bizstats_stripe_billing-0.1.0.dist-info/METADATA
bizstats_stripe_billing-0.1.0.dist-info/WHEEL
bizstats_stripe_billing-0.1.0.dist-info/RECORD
